lightnlp/__init__.py
lightnlp/base/__init__.py
lightnlp/base/config.py
lightnlp/base/model.py
lightnlp/base/module.py
lightnlp/base/tool.py
lightnlp/sl/__init__.py
lightnlp/sl/cws/__init__.py
lightnlp/sl/cws/config.py
lightnlp/sl/cws/model.py
lightnlp/sl/cws/module.py
lightnlp/sl/cws/tool.py
lightnlp/sl/cws/utils/__init__.py
lightnlp/sl/cws/utils/convert.py
lightnlp/sl/ner/__init__.py
lightnlp/sl/ner/config.py
lightnlp/sl/ner/model.py
lightnlp/sl/ner/module.py
lightnlp/sl/ner/tool.py
lightnlp/sl/ner/utils/__init__.py
lightnlp/sl/ner/utils/convert.py
lightnlp/sl/pos/__init__.py
lightnlp/sl/pos/config.py
lightnlp/sl/pos/model.py
lightnlp/sl/pos/module.py
lightnlp/sl/pos/tool.py
lightnlp/sl/pos/utils/__init__.py
lightnlp/sl/pos/utils/convert.py
lightnlp/sl/srl/__init__.py
lightnlp/sl/srl/config.py
lightnlp/sl/srl/model.py
lightnlp/sl/srl/module.py
lightnlp/sl/srl/tool.py
lightnlp/sl/srl/utils/__init__.py
lightnlp/sl/srl/utils/convert.py
lightnlp/sp/__init__.py
lightnlp/sp/gdp/__init__.py
lightnlp/sp/gdp/config.py
lightnlp/sp/gdp/model.py
lightnlp/sp/gdp/module.py
lightnlp/sp/gdp/tool.py
lightnlp/sp/gdp/components/__init__.py
lightnlp/sp/gdp/components/biaffine.py
lightnlp/sp/gdp/components/dropout.py
lightnlp/sp/gdp/components/lstm.py
lightnlp/sp/gdp/components/mlp.py
lightnlp/sp/gdp/utils/__init__.py
lightnlp/sp/gdp/utils/dataset.py
lightnlp/sp/gdp/utils/metric.py
lightnlp/sp/gdp/utils/reader.py
lightnlp/sp/gdp/utils/vocab.py
lightnlp/sp/tdp/__init__.py
lightnlp/sp/tdp/config.py
lightnlp/sp/tdp/model.py
lightnlp/sp/tdp/module.py
lightnlp/sp/tdp/tool.py
lightnlp/sp/tdp/components/__init__.py
lightnlp/sp/tdp/components/action_chooser.py
lightnlp/sp/tdp/components/combiner.py
lightnlp/sp/tdp/components/word_embedding.py
lightnlp/sp/tdp/utils/__init__.py
lightnlp/sp/tdp/utils/dataset.py
lightnlp/sp/tdp/utils/feature_extractor.py
lightnlp/sp/tdp/utils/parser_state.py
lightnlp/sp/tdp/utils/vectors.py
lightnlp/sr/__init__.py
lightnlp/sr/ss/__init__.py
lightNLP-0.4.1.1.dist-info/LICENSE
lightNLP-0.4.1.1.dist-info/METADATA
lightNLP-0.4.1.1.dist-info/WHEEL
lightNLP-0.4.1.1.dist-info/top_level.txt
lightNLP-0.4.1.1.dist-info/RECORD
