Metadata-Version: 2.1
Name: lightNLP
Version: 0.4.1.1
Summary: lightsmile's nlp library
Home-page: https://github.com/smilelight/lightNLP
Author: lightsmile
Author-email: iamlightsmile@gmail.com
License: Apache-2.0
Platform: UNKNOWN
Classifier: Development Status :: 4 - Beta
Classifier: Operating System :: OS Independent
Classifier: Intended Audience :: Developers
Classifier: License :: OSI Approved :: BSD License
Classifier: Programming Language :: Python
Classifier: Programming Language :: Python :: 3
Classifier: Programming Language :: Python :: 3.6
Classifier: Programming Language :: Python :: 3.7
Classifier: Topic :: Software Development :: Libraries
Requires-Dist: torchtext
Requires-Dist: tqdm
Requires-Dist: torch
Requires-Dist: pytorch-crf
Requires-Dist: scikit-learn
Requires-Dist: revtok
Requires-Dist: jieba
Requires-Dist: regex
Requires-Dist: nltk
Requires-Dist: torchcrf
Requires-Dist: flask
